{
  "posts": [
    { "id": 1, "title": "Post 1" },
    { "id": 2, "title": "Post 2" },
    { "id": 3, "title": "Post 3" }
  ],
  "comments": [
    { "id": 1, "body": "some comment", "postId": 1 },
    { "id": 2, "body": "some comment", "postId": 1 }
  ],
  "profile": {
    "name": "typicode"
  },
  "titulos": [
   {
      "id": 1,
      "nombre": "Primera Division",
      "cantidad": 35,
      "titulo": "Nacional"
   },
   {
      "id": 2,
      "nombre": "Copa Intercontinental ",
      "cantidad": 3,
      "titulo": "Internacional"
   },
   {
      "id": 3,
      "nombre": "Libertadores",
      "cantidad": 6,
      "titulo": "Internacional"
   },
   {
      "id": 4,
      "nombre": "Sudamericana",
      "cantidad": 2,
      "titulo": "internacional"
   }
     {
      "id": 5,
      "nombre": "Recopa Sudamericana",
      "cantidad": 4,
      "titulo": "internacional"
   } 
  {
      "id": 6,
      "nombre": "Otros Titulos Nacionales",
      "cantidad": 17,
      "titulo": "Nacional"
   }
 {
      "id": 7,
      "nombre": "Otros Titulos Internacionales",
      "cantidad": 7,
      "titulo": "Internacional"
   }
]
}
